MANIFEST.in
README.markdown
requirements.txt
setup.py
pin/__init__.py
pin/plugins/__init__.py
pin/plugins/autovenv.py
pin/plugins/venv.py
pinvenv.egg-info/PKG-INFO
pinvenv.egg-info/SOURCES.txt
pinvenv.egg-info/dependency_links.txt
pinvenv.egg-info/namespace_packages.txt
pinvenv.egg-info/requires.txt
pinvenv.egg-info/top_level.txt