Metadata-Version: 1.1
Name: pinvenv
Version: 0.1rc1
Summary: VirtualEnv plugins for pin
Home-page: https://github.com/dustinlacewell/pin-venv
Author: Dustin Lacewell
Author-email: dlacewell@gmail.com
License: UNKNOWN
Platform: UNKNOWN
Provides: pinvenv
